nerdd_link/__init__.py
nerdd_link/py.typed
nerdd_link/version.py
nerdd_link/actions/__init__.py
nerdd_link/actions/action.py
nerdd_link/actions/predict_checkpoints_action.py
nerdd_link/actions/process_jobs_action.py
nerdd_link/actions/serialize_job_action.py
nerdd_link/channels/__init__.py
nerdd_link/channels/channel.py
nerdd_link/channels/kafka_channel.py
nerdd_link/channels/memory_channel.py
nerdd_link/cli/__init__.py
nerdd_link/cli/run_job_server.py
nerdd_link/cli/run_prediction_server.py
nerdd_link/cli/run_serialization_server.py
nerdd_link/converters/__init__.py
nerdd_link/converters/image_converter.py
nerdd_link/converters/mol_pickle_converter.py
nerdd_link/converters/mol_to_image_converter.py
nerdd_link/converters/pickle_converter.py
nerdd_link/converters/problem_list_converter.py
nerdd_link/converters/source_list_converter.py
nerdd_link/delegates/__init__.py
nerdd_link/delegates/predict_checkpoint_model.py
nerdd_link/files/__init__.py
nerdd_link/files/file_system.py
nerdd_link/input/__init__.py
nerdd_link/input/structure_json_reader.py
nerdd_link/output/__init__.py
nerdd_link/output/channel_writer.py
nerdd_link/output/pickle_writer.py
nerdd_link/steps/__init__.py
nerdd_link/steps/add_record_id_step.py
nerdd_link/steps/postprocess_from_config_step.py
nerdd_link/steps/read_pickle_step.py
nerdd_link/steps/replace_large_properties_step.py
nerdd_link/steps/split_and_merge_step.py
nerdd_link/steps/wrap_results_step.py
nerdd_link/steps/write_checkpoints_step.py
nerdd_link/tests/__init__.py
nerdd_link/tests/async_step.py
nerdd_link/tests/channels.py
nerdd_link/tests/files.py
nerdd_link/types/__init__.py
nerdd_link/utils/__init__.py
nerdd_link/utils/async_to_sync.py
nerdd_link/utils/batched.py
nerdd_link/utils/observable_list.py
nerdd_link/utils/run_pipeline.py
nerdd_link/utils/safetee.py
nerdd_link-0.5.14.dist-info/licenses/LICENSE
nerdd_link-0.5.14.dist-info/METADATA
nerdd_link-0.5.14.dist-info/WHEEL
nerdd_link-0.5.14.dist-info/entry_points.txt
nerdd_link-0.5.14.dist-info/top_level.txt
nerdd_link-0.5.14.dist-info/RECORD
