Metadata-Version: 2.4
Name: nerdd-link
Version: 0.5.14
Summary: Run a NERDD module as a service
Author-email: Steffen Hirte <steffen.hirte@univie.ac.at>
Maintainer-email: Steffen Hirte <steffen.hirte@univie.ac.at>
License-Expression: BSD-3-Clause
Project-URL: Repository, https://github.com/molinfo-vienna/nerdd-link
Keywords: science,research,development,nerdd
Classifier: Intended Audience :: Science/Research
Classifier: Intended Audience :: Developers
Classifier: Programming Language :: Python
Classifier: Topic :: Software Development
Classifier: Topic :: Scientific/Engineering
Classifier: Operating System :: Microsoft :: Windows
Classifier: Operating System :: POSIX
Classifier: Operating System :: Unix
Classifier: Operating System :: MacOS
Classifier: Programming Language :: Python :: 3
Classifier: Programming Language :: Python :: 3.9
Classifier: Programming Language :: Python :: 3.10
Classifier: Programming Language :: Python :: 3.11
Classifier: Programming Language :: Python :: 3.12
License-File: LICENSE
Requires-Dist: nerdd-module>=0.3.44
Requires-Dist: pandas>=1.2.1
Requires-Dist: pyyaml~=6.0
Requires-Dist: filetype~=1.2.0
Requires-Dist: rich-click>=1.7.1
Requires-Dist: stringcase~=1.2.0
Requires-Dist: numpy
Requires-Dist: simplejson>=3
Requires-Dist: pydantic>=2
Requires-Dist: aiokafka>=0.12.0
Requires-Dist: importlib-metadata>=4.6; python_version < "3.10"
Requires-Dist: typing_extensions>=4.0.1; python_version < "3.8"
Provides-Extra: dev
Requires-Dist: mypy; extra == "dev"
Requires-Dist: ruff==0.8.0; extra == "dev"
Requires-Dist: pre-commit>=2; extra == "dev"
Provides-Extra: test
Requires-Dist: pytest; extra == "test"
Requires-Dist: pytest-sugar; extra == "test"
Requires-Dist: pytest-cov; extra == "test"
Requires-Dist: pytest-asyncio~=0.21.1; extra == "test"
Requires-Dist: pytest-bdd==7.3.0; extra == "test"
Requires-Dist: pytest-mock; extra == "test"
Requires-Dist: pytest-watcher; extra == "test"
Requires-Dist: hypothesis; extra == "test"
Requires-Dist: hypothesis-rdkit; extra == "test"
Provides-Extra: docs
Requires-Dist: mkdocs; extra == "docs"
Requires-Dist: mkdocs-material; extra == "docs"
Requires-Dist: mkdocstrings; extra == "docs"
Dynamic: license-file
